<?xml version="1.0" encoding="UTF-8"?>
<!DOCTYPE mapper PUBLIC "-//mybatis.org//DTD Mapper 3.0//EN" "http://mybatis.org/dtd/mybatis-3-mapper.dtd">

<mapper namespace="io.renren.modules.region.dao.SysRegionDao">

    <select id="getOldRegion" resultType="map">
        SELECT * from sys_region2
        <where>
            <if test="id != '' and id != null">
                and id = #{id}
            </if>
            <if test="name != '' and name != null">
                and name = #{name}
            </if>
            <if test="pid != '' and pid != null">
                and pid = #{pid}
            </if>
        </where>
    </select>
</mapper>